ip2mokapot/__init__.py
ip2mokapot/config.py
ip2mokapot/filter.py
ip2mokapot/parsing.py
ip2mokapot/util.py
ip2mokapot/mokapot/__init__.py
ip2mokapot/mokapot/brew.py
ip2mokapot/mokapot/confidence.py
ip2mokapot/mokapot/config.py
ip2mokapot/mokapot/dataset.py
ip2mokapot/mokapot/model.py
ip2mokapot/mokapot/mokapot.py
ip2mokapot/mokapot/peptides.py
ip2mokapot/mokapot/picked_protein.py
ip2mokapot/mokapot/proteins.py
ip2mokapot/mokapot/qvalues.py
ip2mokapot/mokapot/utils.py
ip2mokapot/mokapot/parsers/__init__.py
ip2mokapot/mokapot/parsers/fasta.py
ip2mokapot/mokapot/parsers/pepxml.py
ip2mokapot/mokapot/parsers/pin.py
ip2mokapot/mokapot/plugins/__init__.py
ip2mokapot/mokapot/writers/__init__.py
ip2mokapot/mokapot/writers/flashlfq.py
ip2mokapot/mokapot/writers/txt.py
ip2mokapot-0.1.9.dist-info/LICENSE
ip2mokapot-0.1.9.dist-info/METADATA
ip2mokapot-0.1.9.dist-info/WHEEL
ip2mokapot-0.1.9.dist-info/entry_points.txt
ip2mokapot-0.1.9.dist-info/top_level.txt
ip2mokapot-0.1.9.dist-info/RECORD
