Metadata-Version: 2.1
Name: ip2mokapot
Version: 0.1.9
Home-page: 
Author: pgarrett
Author-email: pgarrett@scripps.edu
Requires-Python: >=3.6
License-File: LICENSE
Requires-Dist: numpy (==1.23.5)
Requires-Dist: pandas (==1.5.2)
Requires-Dist: serenipy (==0.2.5)
Requires-Dist: xgboost (==1.7.3)
Requires-Dist: biopython (==1.80)
Requires-Dist: streamlit (==1.17.0)
Requires-Dist: tabulate (==0.9.0)
Requires-Dist: peptacular (==0.0.3)
